ai/__init__.py
ai/dive/__init__.py
ai/dive/diver.py
ai/dive/saver.py
ai/dive/trainer.py
ai/dive/data/dataset.py
ai/dive/data/directory_classification.py
ai/dive/data/file_classification.py
ai/dive/data/image_file_classification.py
ai/dive/data/label_reader.py
ai/dive/data/prompt_repeater.py
ai/dive/data/prompt_template_filler.py
ai/dive/models/__init__.py
ai/dive/models/clip.py
ai/dive/models/gpt4.py
ai/dive/models/image_classification.py
ai/dive/models/model.py
ai/dive/models/resnet50.py
ai/dive/models/vit.py
ai_dive-0.0.1.dist-info/LICENSE
ai_dive-0.0.1.dist-info/METADATA
ai_dive-0.0.1.dist-info/WHEEL
ai_dive-0.0.1.dist-info/top_level.txt
ai_dive-0.0.1.dist-info/RECORD
