Metadata-Version: 2.1
Name: ai-dive
Version: 0.0.1
Summary: Framework to help you dive into AI
Author-email: Greg Schoeninger <g@oxen.ai>
Project-URL: Homepage, https://oxen.ai/
Project-URL: Source, https://github.com/Oxen-AI/AI-Dive
Classifier: Programming Language :: Python :: Implementation :: PyPy
Requires-Python: >=3.7
License-File: LICENSE
Requires-Dist: pandas ==2.0.1
Requires-Dist: opencv-python ==4.7.0.72
Requires-Dist: numpy ==1.24.3
Requires-Dist: tqdm ==4.65.0
Requires-Dist: toml ==0.10.2
Requires-Dist: transformers ==4.30.1
Requires-Dist: datasets ==2.14.5
